policyengine_api_simulation_client/__init__.py
policyengine_api_simulation_client/api/__init__.py
policyengine_api_simulation_client/api/default/__init__.py
policyengine_api_simulation_client/api/default/get_country_versions_versions_country_get.py
policyengine_api_simulation_client/api/default/get_job_status_jobs_job_id_get.py
policyengine_api_simulation_client/api/default/health_health_get.py
policyengine_api_simulation_client/api/default/list_versions_versions_get.py
policyengine_api_simulation_client/api/default/ping_ping_post.py
policyengine_api_simulation_client/api/default/submit_simulation_simulate_economy_comparison_post.py
policyengine_api_simulation_client/client.py
policyengine_api_simulation_client/errors.py
policyengine_api_simulation_client/models/__init__.py
policyengine_api_simulation_client/models/get_country_versions_versions_country_get_response_get_country_versions_versions_country_get.py
policyengine_api_simulation_client/models/health_health_get_response_health_health_get.py
policyengine_api_simulation_client/models/http_validation_error.py
policyengine_api_simulation_client/models/job_status_response.py
policyengine_api_simulation_client/models/job_status_response_result_type_0.py
policyengine_api_simulation_client/models/job_submit_response.py
policyengine_api_simulation_client/models/list_versions_versions_get_response_list_versions_versions_get.py
policyengine_api_simulation_client/models/ping_request.py
policyengine_api_simulation_client/models/ping_response.py
policyengine_api_simulation_client/models/simulation_request.py
policyengine_api_simulation_client/models/validation_error.py
policyengine_api_simulation_client/py.typed
policyengine_api_simulation_client/types.py
policyengine_api_simulation_client-0.20260130.88.dist-info/METADATA
policyengine_api_simulation_client-0.20260130.88.dist-info/WHEEL
policyengine_api_simulation_client-0.20260130.88.dist-info/RECORD
